drf_oauth_toolkit/__init__.py
drf_oauth_toolkit/admin.py
drf_oauth_toolkit/asgi.py
drf_oauth_toolkit/decorators.py
drf_oauth_toolkit/exceptions.py
drf_oauth_toolkit/migrations/0001_initial.py
drf_oauth_toolkit/migrations/__init__.py
drf_oauth_toolkit/models.py
drf_oauth_toolkit/services/__init__.py
drf_oauth_toolkit/services/base.py
drf_oauth_toolkit/services/google.py
drf_oauth_toolkit/services/microsoft.py
drf_oauth_toolkit/services/twitter.py
drf_oauth_toolkit/settings.py
drf_oauth_toolkit/urls.py
drf_oauth_toolkit/utils/__init__.py
drf_oauth_toolkit/utils/commons.py
drf_oauth_toolkit/utils/fields.py
drf_oauth_toolkit/utils/settings_loader.py
drf_oauth_toolkit/utils/state_helpers.py
drf_oauth_toolkit/utils/token_management.py
drf_oauth_toolkit/views/__init__.py
drf_oauth_toolkit/views/base.py
drf_oauth_toolkit/views/google_views.py
drf_oauth_toolkit/views/microsoft_views.py
drf_oauth_toolkit/views/twitter_views.py
drf_oauth_toolkit/wsgi.py
drf_oauth_toolkit-0.1.2.dist-info/LICENSE
drf_oauth_toolkit-0.1.2.dist-info/METADATA
drf_oauth_toolkit-0.1.2.dist-info/WHEEL
drf_oauth_toolkit-0.1.2.dist-info/RECORD
