Metadata-Version: 2.1
Name: drf-oauth-toolkit
Version: 0.1.2
Summary: A toolkit for handling OAuth with Django Rest Framework
License: MIT
Author: Basel Mahmoud
Author-email: basel.mahmoud@arkleap.com
Requires-Python: >=3.10,<4.0
Classifier: License :: OSI Approved :: MIT License
Classifier: Programming Language :: Python :: 3
Classifier: Programming Language :: Python :: 3.10
Classifier: Programming Language :: Python :: 3.11
Classifier: Programming Language :: Python :: 3.12
Classifier: Programming Language :: Python :: 3.13
Requires-Dist: attrs (>=24.3.0,<25.0.0)
Requires-Dist: cryptography (>=44.0.0,<45.0.0)
Requires-Dist: django (>=5.1.4,<6.0.0)
Requires-Dist: djangorestframework (>=3.15.2,<4.0.0)
Requires-Dist: djangorestframework-simplejwt (>=5.4.0,<6.0.0)
Requires-Dist: oauthlib (>=3.2.2,<4.0.0)
Requires-Dist: pyjwt (>=2.10.1,<3.0.0)
Requires-Dist: requests (>=2.32.3,<3.0.0)
Requires-Dist: types-requests (>=2.32.0.20241016,<3.0.0.0)
